CHANGELOG.md
LICENSE
MANIFEST.in
Makefile
README.md
setup.cfg
setup.py
tox.ini
px_access_scopes/__init__.py
px_access_scopes/aggregates.py
px_access_scopes/exceptions.py
px_access_scopes/export.py
px_access_scopes/scopes.py
px_access_scopes/utils.py
px_access_scopes.egg-info/PKG-INFO
px_access_scopes.egg-info/SOURCES.txt
px_access_scopes.egg-info/dependency_links.txt
px_access_scopes.egg-info/requires.txt
px_access_scopes.egg-info/top_level.txt
px_access_scopes/checkers/__init__.py
px_access_scopes/checkers/base.py
px_access_scopes/checkers/checkers.py
px_access_scopes/checkers/mixins.py
px_access_scopes/checkers/multiregistry.py
px_access_scopes/checkers/runner.py
px_access_scopes/contrib/__init__.py
px_access_scopes/contrib/django/__init__.py
px_access_scopes/contrib/django/aggregates.py
px_access_scopes/contrib/django/apps.py
px_access_scopes/contrib/django/checkers.py
px_access_scopes/contrib/django/conf.py
px_access_scopes/contrib/django/discover.py
px_access_scopes/contrib/django/export.py
px_access_scopes/contrib/django/globals.py
px_access_scopes/contrib/django/models.py
px_access_scopes/contrib/django/scopes.py
px_access_scopes/contrib/django/subscriptions.py
px_access_scopes/contrib/django/utils.py
px_access_scopes/contrib/django/generator/__init__.py
px_access_scopes/contrib/django/generator/all.py
px_access_scopes/contrib/django/generator/groups.py
px_access_scopes/contrib/django/generator/permissions.py
px_access_scopes/contrib/drf/__init__.py
px_access_scopes/contrib/drf/apps.py
px_access_scopes/contrib/drf/permissions.py
tests/test_aggregates.py
tests/test_checkers.py
tests/test_scope_registry.py
tests/test_tree_generator.py